Metadata-Version: 2.1
Name: odoo13-addon-rest-log
Version: 13.0.1.5.0
Summary: Track REST API calls into DB
Home-page: https://github.com/OCA/rest-framework
Author: Camptocamp, ACSONE, Odoo Community Association (OCA)
Author-email: support@odoo-community.org
License: LGPL-3
Platform: UNKNOWN
Classifier: Programming Language :: Python
Classifier: Framework :: Odoo
Classifier: Framework :: Odoo :: 13.0
Classifier: License :: OSI Approved :: GNU Lesser General Public License v3 (LGPLv3)
Classifier: Development Status :: 3 - Alpha
Requires-Python: >=3.5
Requires-Dist: odoo13-addon-base-rest
Requires-Dist: odoo (<13.1dev,>=13.0a)
